MANIFEST.in
README.md
README.rst
setup.cfg
setup.py
article/__init__.py
article/admin.py
article/apps.py
article/models.py
article/tests.py
article/urls.py
article/views.py
article/fixtures/articles.json
article/migrations/0001_initial.py
article/migrations/0002_article_tags.py
article/migrations/__init__.py
article/templates/article/base.html
article/templates/article/detail.html
article/templates/article/list.html
article/templatetags/__init__.py
article/templatetags/article_tags.py
simple_article.egg-info/PKG-INFO
simple_article.egg-info/SOURCES.txt
simple_article.egg-info/dependency_links.txt
simple_article.egg-info/requires.txt
simple_article.egg-info/top_level.txt