Metadata-Version: 1.1
Name: simple-article
Version: 0.2.1
Summary: Provide deadly simple Article model for Django
Home-page: https://github.com/zniper/simple-article
Author: Ha Pham
Author-email: me.zniper@gmail.com
License: MIT
Keywords: article model simple django entry blog
Platform: UNKNOWN
Classifier: Development Status :: 5 - Production/Stable
Classifier: Intended Audience :: Developers
Classifier: Topic :: Software Development :: Build Tools
Classifier: License :: OSI Approved :: MIT License
Classifier: Programming Language :: Python :: 2
Classifier: Programming Language :: Python :: 2.6
Classifier: Programming Language :: Python :: 2.7
Classifier: Programming Language :: Python :: 3
Classifier: Programming Language :: Python :: 3.2
Classifier: Programming Language :: Python :: 3.3
Classifier: Programming Language :: Python :: 3.4
